wd_crawler_client/__init__.py
wd_crawler_client/crawler/__init__.py
wd_crawler_client/lib/__init__.py
wd_crawler_client/lib/config.py
wd_crawler_client/lib/hqueue.py
wd_crawler_client/lib/mail.py
wd_crawler_client/lib/md5.py
wd_crawler_client/lib/queue.py
wd_crawler_client/lib/store_mysql.py
wd_crawler_client/lib/user_agents.py
wd_crawler_client-6.0.2.dist-info/METADATA
wd_crawler_client-6.0.2.dist-info/WHEEL
wd_crawler_client-6.0.2.dist-info/top_level.txt
wd_crawler_client-6.0.2.dist-info/RECORD
