Metadata-Version: 2.1
Name: wd-crawler-client
Version: 6.0.2
Summary: spider framework for winndoo.
Home-page: http://git.winndoo.cn:82/python/download_center/downloader_client.git
Author: mingwei.jie baozhu.zhang
Author-email: baozhu.zhang@winndoo.com
License: UNKNOWN
Keywords: crawler,wendao
Platform: UNKNOWN
Requires-Python: >=3.6.0
Requires-Dist: mysqlclient (>=1.4.6)
Requires-Dist: Twisted (>=18.9.0)
Requires-Dist: treq (>=18.6.0)
